README.rst
setup.py
marbaloo_validators/__init__.py
marbaloo_validators.egg-info/PKG-INFO
marbaloo_validators.egg-info/SOURCES.txt
marbaloo_validators.egg-info/dependency_links.txt
marbaloo_validators.egg-info/requires.txt
marbaloo_validators.egg-info/top_level.txt
test/testcase.py